[{"pk": 1, "model": "quote.locationrelation", "fields": {"packer": 1, "customer": 18, "destination": "NEW YORK", "location": "US"}}, {"pk": 2, "model": "quote.locationrelation", "fields": {"packer": 1, "customer": 1, "destination": "MONTREAL", "location": "Can"}}, {"pk": 3, "model": "quote.locationrelation", "fields": {"packer": 1, "customer": 19, "destination": "NEW YORK", "location": "US"}}, {"pk": 4, "model": "quote.locationrelation", "fields": {"packer": 1, "customer": 20, "destination": "NEW YORK", "location": "US"}}, {"pk": 5, "model": "quote.locationrelation", "fields": {"packer": 1, "customer": 21, "destination": "NEW YORK", "location": "US"}}, {"pk": 6, "model": "quote.locationrelation", "fields": {"packer": 1, "customer": 22, "destination": "NEW YORK", "location": "US"}}, {"pk": 7, "model": "quote.locationrelation", "fields": {"packer": 1, "customer": 23, "destination": "NEW YORK", "location": "US"}}, {"pk": 8, "model": "quote.locationrelation", "fields": {"packer": 1, "customer": 24, "destination": "NEW YORK", "location": "US"}}, {"pk": 9, "model": "quote.locationrelation", "fields": {"packer": 1, "customer": 4, "destination": "VANCOUVER", "location": "Can"}}, {"pk": 10, "model": "quote.locationrelation", "fields": {"packer": 1, "customer": 9, "destination": "CALGARY", "location": "Can"}}, {"pk": 11, "model": "quote.locationrelation", "fields": {"packer": 1, "customer": 10, "destination": "VANCOUVER", "location": "Can"}}, {"pk": 12, "model": "quote.locationrelation", "fields": {"packer": 1, "customer": 3, "destination": "LA", "location": "Can"}}, {"pk": 13, "model": "quote.locationrelation", "fields": {"packer": 3, "customer": 1, "destination": "VANCOUVER", "location": "Can"}}, {"pk": 14, "model": "quote.locationrelation", "fields": {"packer": 3, "customer": 8, "destination": "CALGARY", "location": "Can"}}, {"pk": 15, "model": "quote.locationrelation", "fields": {"packer": 1, "customer": 25, "destination": "CALGARY", "location": "Can"}}, {"pk": 18, "model": "quote.locationrelation", "fields": {"packer": 1, "customer": null, "destination": "LA", "location": "US"}}]